geosink/__init__.py
geosink/cheb_approx.py
geosink/heat_kernel.py
geosink/sinkhorn.py
geosink-0.2.0.dist-info/LICENSE
geosink-0.2.0.dist-info/METADATA
geosink-0.2.0.dist-info/WHEEL
geosink-0.2.0.dist-info/top_level.txt
geosink-0.2.0.dist-info/RECORD
