Metadata-Version: 2.1
Name: geosink
Version: 0.2.0
Summary: Geodesic Sinkhorn with Chebyshev approximation
Author: Guillaume Huguet
License: MIT License
Keywords: diffusion,optimal transport,heat,kernel,sinkhorn
Requires-Python: >=3.8
License-File: LICENSE
Requires-Dist: scipy
Requires-Dist: numpy
Provides-Extra: dev
Requires-Dist: black ; extra == 'dev'
Requires-Dist: pylint ; extra == 'dev'
Requires-Dist: pytest ; extra == 'dev'
Requires-Dist: isort ; extra == 'dev'
Requires-Dist: scanpy ; extra == 'dev'
Requires-Dist: pygsp ; extra == 'dev'
Requires-Dist: pytest-memray ; extra == 'dev'
Provides-Extra: graph
Requires-Dist: scanpy ; extra == 'graph'
Requires-Dist: pygsp ; extra == 'graph'
